haystack/__init__.py
haystack/errors.py
haystack/lazy_imports.py
haystack/logging.py
haystack/py.typed
haystack/version.py
haystack/components/__init__.py
haystack/components/agents/__init__.py
haystack/components/agents/agent.py
haystack/components/agents/state/__init__.py
haystack/components/agents/state/state.py
haystack/components/agents/state/state_utils.py
haystack/components/audio/__init__.py
haystack/components/audio/whisper_local.py
haystack/components/audio/whisper_remote.py
haystack/components/builders/__init__.py
haystack/components/builders/answer_builder.py
haystack/components/builders/chat_prompt_builder.py
haystack/components/builders/prompt_builder.py
haystack/components/caching/__init__.py
haystack/components/caching/cache_checker.py
haystack/components/classifiers/__init__.py
haystack/components/classifiers/document_language_classifier.py
haystack/components/classifiers/zero_shot_document_classifier.py
haystack/components/connectors/__init__.py
haystack/components/connectors/openapi.py
haystack/components/connectors/openapi_service.py
haystack/components/converters/__init__.py
haystack/components/converters/azure.py
haystack/components/converters/csv.py
haystack/components/converters/docx.py
haystack/components/converters/html.py
haystack/components/converters/json.py
haystack/components/converters/markdown.py
haystack/components/converters/msg.py
haystack/components/converters/multi_file_converter.py
haystack/components/converters/openapi_functions.py
haystack/components/converters/output_adapter.py
haystack/components/converters/pdfminer.py
haystack/components/converters/pptx.py
haystack/components/converters/pypdf.py
haystack/components/converters/tika.py
haystack/components/converters/txt.py
haystack/components/converters/utils.py
haystack/components/converters/xlsx.py
haystack/components/converters/image/__init__.py
haystack/components/converters/image/document_to_image.py
haystack/components/converters/image/file_to_document.py
haystack_ai-2.22.0.dist-info/METADATA
haystack_ai-2.22.0.dist-info/WHEEL
haystack_ai-2.22.0.dist-info/licenses/LICENSE
haystack_ai-2.22.0.dist-info/RECORD
