Metadata-Version: 2.4
Name: haystack-ai
Version: 2.22.0
Summary: LLM framework to build customizable, production-ready LLM applications. Connect components (models, vector DBs, file converters) to pipelines or agents that can interact with your data.
Project-URL: CI: GitHub, https://github.com/deepset-ai/haystack/actions
Project-URL: Docs: RTD, https://haystack.deepset.ai/overview/intro
Project-URL: GitHub: issues, https://github.com/deepset-ai/haystack/issues
Project-URL: GitHub: repo, https://github.com/deepset-ai/haystack
Project-URL: Homepage, https://github.com/deepset-ai/haystack
Author-email: "deepset.ai" <malte.pietsch@deepset.ai>
License-Expression: Apache-2.0
License-File: LICENSE
Keywords: BERT,QA,Question-Answering,Reader,Retriever,albert,language-model,mrc,roberta,search,semantic-search,squad,transfer-learning,transformer
Classifier: Development Status :: 5 - Production/Stable
Classifier: Intended Audience :: Science/Research
Classifier: License :: Freely Distributable
Classifier: License :: OSI Approved :: Apache Software License
Classifier: Operating System :: OS Independent
Classifier: Programming Language :: Python
Classifier: Programming Language :: Python :: 3
Classifier: Programming Language :: Python :: 3.10
Classifier: Programming Language :: Python :: 3.11
Classifier: Programming Language :: Python :: 3.12
Classifier: Programming Language :: Python :: 3.13
Classifier: Topic :: Scientific/Engineering :: Artificial Intelligence
Requires-Python: >=3.10
Requires-Dist: docstring-parser
Requires-Dist: filetype
Requires-Dist: haystack-experimental
Requires-Dist: jinja2
Requires-Dist: jsonschema
Requires-Dist: lazy-imports
Requires-Dist: more-itertools
Requires-Dist: networkx
Requires-Dist: numpy
Requires-Dist: openai>=1.99.2
Requires-Dist: posthog!=3.12.0
Requires-Dist: pydantic
Requires-Dist: python-dateutil
Requires-Dist: pyyaml
Requires-Dist: requests
Requires-Dist: tenacity!=8.4.0
Requires-Dist: tqdm
Requires-Dist: typing-extensions>=4.7
